<?xml version="1.0" encoding="utf-8" ?>
<dwsync>
<file name="index.php" server="1010richards.com/popdigital/htdocs/" local="129455100000000000" remote="129455100000000000" />
<file name="wp-table-reloaded-ar.mo" server="1010richards.com/popdigital/htdocs/" local="129455100000000000" remote="129455100000000000" />
<file name="wp-table-reloaded-ar.po" server="1010richards.com/popdigital/htdocs/" local="129455100000000000" remote="129455100000000000" />
<file name="wp-table-reloaded-be_BY.mo" server="1010richards.com/popdigital/htdocs/" local="129455100000000000" remote="129455100000000000" />
<file name="wp-table-reloaded-be_BY.po" server="1010richards.com/popdigital/htdocs/" local="129455100000000000" remote="129455100000000000" />
<file name="wp-table-reloaded-cs_CZ.mo" server="1010richards.com/popdigital/htdocs/" local="129455100000000000" remote="129455100000000000" />
<file name="wp-table-reloaded-cs_CZ.po" server="1010richards.com/popdigital/htdocs/" local="129455100000000000" remote="129455100000000000" />
<file name="wp-table-reloaded-de_DE.mo" server="1010richards.com/popdigital/htdocs/" local="129455100000000000" remote="129455100000000000" />
<file name="wp-table-reloaded-de_DE.po" server="1010richards.com/popdigital/htdocs/" local="129455100000000000" remote="129455100000000000" />
<file name="wp-table-reloaded-es_ES.mo" server="1010richards.com/popdigital/htdocs/" local="129455100000000000" remote="129455100000000000" />
<file name="wp-table-reloaded-es_ES.po" server="1010richards.com/popdigital/htdocs/" local="129455100000000000" remote="129455100000000000" />
<file name="wp-table-reloaded-fi_FI.mo" server="1010richards.com/popdigital/htdocs/" local="129455100000000000" remote="129455100000000000" />
<file name="wp-table-reloaded-fi_FI.po" server="1010richards.com/popdigital/htdocs/" local="129455100000000000" remote="129455100000000000" />
<file name="wp-table-reloaded-fr_FR.mo" server="1010richards.com/popdigital/htdocs/" local="129455100000000000" remote="129455100000000000" />
<file name="wp-table-reloaded-fr_FR.po" server="1010richards.com/popdigital/htdocs/" local="129455100000000000" remote="129455100000000000" />
<file name="wp-table-reloaded-hi_IN.mo" server="1010richards.com/popdigital/htdocs/" local="129455100000000000" remote="129455100000000000" />
<file name="wp-table-reloaded-hi_IN.po" server="1010richards.com/popdigital/htdocs/" local="129455100000000000" remote="129455100000000000" />
<file name="wp-table-reloaded-id_ID.mo" server="1010richards.com/popdigital/htdocs/" local="129455100000000000" remote="129455100000000000" />
<file name="wp-table-reloaded-id_ID.po" server="1010richards.com/popdigital/htdocs/" local="129455100000000000" remote="129455100000000000" />
<file name="wp-table-reloaded-it_IT.mo" server="1010richards.com/popdigital/htdocs/" local="129455100000000000" remote="129455100000000000" />
<file name="wp-table-reloaded-it_IT.po" server="1010richards.com/popdigital/htdocs/" local="129455100000000000" remote="129455100000000000" />
<file name="wp-table-reloaded-ja.mo" server="1010richards.com/popdigital/htdocs/" local="129455100000000000" remote="129455100000000000" />
<file name="wp-table-reloaded-ja.po" server="1010richards.com/popdigital/htdocs/" local="129455100000000000" remote="129455100000000000" />
<file name="wp-table-reloaded-nl_NL.mo" server="1010richards.com/popdigital/htdocs/" local="129455100000000000" remote="129455100000000000" />
<file name="wp-table-reloaded-nl_NL.po" server="1010richards.com/popdigital/htdocs/" local="129455100000000000" remote="129455100000000000" />
<file name="wp-table-reloaded-pl_PL.mo" server="1010richards.com/popdigital/htdocs/" local="129455100000000000" remote="129455100000000000" />
<file name="wp-table-reloaded-pl_PL.po" server="1010richards.com/popdigital/htdocs/" local="129455100000000000" remote="129455100000000000" />
<file name="wp-table-reloaded-pt_BR.mo" server="1010richards.com/popdigital/htdocs/" local="129455100000000000" remote="129455100000000000" />
<file name="wp-table-reloaded-pt_BR.po" server="1010richards.com/popdigital/htdocs/" local="129455100000000000" remote="129455100000000000" />
<file name="wp-table-reloaded-ru_RU.mo" server="1010richards.com/popdigital/htdocs/" local="129455100000000000" remote="129455100000000000" />
<file name="wp-table-reloaded-ru_RU.po" server="1010richards.com/popdigital/htdocs/" local="129455100000000000" remote="129455100000000000" />
<file name="wp-table-reloaded-sk_SK.mo" server="1010richards.com/popdigital/htdocs/" local="129455100000000000" remote="129455100000000000" />
<file name="wp-table-reloaded-sk_SK.po" server="1010richards.com/popdigital/htdocs/" local="129455100000000000" remote="129455100000000000" />
<file name="wp-table-reloaded-sv_SE.mo" server="1010richards.com/popdigital/htdocs/" local="129455100000000000" remote="129455100000000000" />
<file name="wp-table-reloaded-sv_SE.po" server="1010richards.com/popdigital/htdocs/" local="129455100000000000" remote="129455100000000000" />
<file name="wp-table-reloaded-ua_UA.mo" server="1010richards.com/popdigital/htdocs/" local="129455100000000000" remote="129455100000000000" />
<file name="wp-table-reloaded-ua_UA.po" server="1010richards.com/popdigital/htdocs/" local="129455100000000000" remote="129455100000000000" />
<file name="wp-table-reloaded-zh_CN.mo" server="1010richards.com/popdigital/htdocs/" local="129455100000000000" remote="129455100000000000" />
<file name="wp-table-reloaded-zh_CN.po" server="1010richards.com/popdigital/htdocs/" local="129455100000000000" remote="129455100000000000" />
<file name="wp-table-reloaded.pot" server="1010richards.com/popdigital/htdocs/" local="129455100000000000" remote="129455100000000000" />
</dwsync>